test/__init__.py
test/dictionary_test.py
test/indexer_test.py
test/model_test.py
test/selector_test.py
test/utils_test.py
test/word_extraction_test.py
xinci/__init__.py
xinci/__init__.pyc
xinci/algorithm.pyc
xinci/common.dic
xinci/dictionary.py
xinci/dictionary.pyc
xinci/indexer.py
xinci/indexer.pyc
xinci/model.py
xinci/model.pyc
xinci/new_words_finder.pyc
xinci/selector.py
xinci/selector.pyc
xinci/test.txt
xinci/utils.py
xinci/utils.pyc
xinci/word_extraction.py
xinci/word_extraction.pyc
xinci-1.2.0.dist-info/DESCRIPTION.rst
xinci-1.2.0.dist-info/METADATA
xinci-1.2.0.dist-info/RECORD
xinci-1.2.0.dist-info/WHEEL
xinci-1.2.0.dist-info/metadata.json
xinci-1.2.0.dist-info/top_level.txt
