Metadata-Version: 2.0
Name: xinci
Version: 1.2.0
Summary: Chinese words extraction and new words discovery
Home-page: https://github.com/lapis-hong/xinci
Author: Lapis-Hong
Author-email: dinghongquan@sjtu.edu.cn
License: MIT
Keywords: NLP,Chinese words extraction,New words discovery
Platform: UNKNOWN
Classifier: Programming Language :: Python :: 2.7
Classifier: Programming Language :: Python :: 3.2
Classifier: Programming Language :: Python :: 3.3
Classifier: Programming Language :: Python :: 3.4
Classifier: Programming Language :: Python :: 3.5
Classifier: Programming Language :: Python :: 3.6
Classifier: Topic :: Scientific/Engineering :: Artificial Intelligence
